JWST_IMAGE_MAKER/__init__.py
JWST_IMAGE_MAKER/importing.py
JWST_IMAGE_MAKER/main.py
JWST_IMAGE_MAKER/plotting.py
JWST_IMAGE_MAKER/processing.py
JWST_IMAGE_MAKER/Input Data/__init__.py
JWST_IMAGE_MAKER-0.1.5.dist-info/LICENSE
JWST_IMAGE_MAKER-0.1.5.dist-info/METADATA
JWST_IMAGE_MAKER-0.1.5.dist-info/WHEEL
JWST_IMAGE_MAKER-0.1.5.dist-info/top_level.txt
JWST_IMAGE_MAKER-0.1.5.dist-info/RECORD
