Metadata-Version: 2.1
Name: JWST-IMAGE-MAKER
Version: 0.1.5
Summary: Creates images from raw JWST data
Home-page: https://github.com/henrywhite2727/JWST_Image_Maker
Author: Henry White and Hansen Jiang
Author-email: henrywhite@sidratresearch.com, hansen@sidratresearch.com
License: Apache License 2.0
License-File: LICENSE
Requires-Dist: numpy
Requires-Dist: astropy.io.fits
Requires-Dist: sys
Requires-Dist: os
Requires-Dist: matplotlib.pyplot
